kryptolib/__init__.py
kryptolib/settings.py
kryptolib/EdDSA/__init__.py
kryptolib/EdDSA/rfc_8032.py
kryptolib-0.0.2.dist-info/LICENSE
kryptolib-0.0.2.dist-info/METADATA
kryptolib-0.0.2.dist-info/WHEEL
kryptolib-0.0.2.dist-info/top_level.txt
kryptolib-0.0.2.dist-info/RECORD
