Metadata-Version: 2.1
Name: kryptolib
Version: 0.0.2
Summary: Krypto library for python
Home-page: https://github.com/subramanya-a/kryptolib
Author: Subramanya A
Author-email: subramanya.opensource@gmail.com
License: MIT license
Keywords: crypto,cryptography,security,DSA,signature,EdDSA,RFC_8032
Platform: any
Classifier: Intended Audience :: End Users/Desktop
Classifier: Topic :: Security :: Cryptography
Classifier: Topic :: Security
Classifier: Development Status :: 5 - Production/Stable
Classifier: Natural Language :: English
Classifier: License :: OSI Approved :: MIT License
Classifier: Operating System :: MacOS :: MacOS X
Classifier: Operating System :: POSIX
Classifier: Operating System :: Unix
Classifier: Programming Language :: Python
Classifier: Programming Language :: Python :: 2
Classifier: Programming Language :: Python :: 3
License-File: LICENSE
